builtin_interfaces/_dummy.cpython-313-x86_64-linux-gnu.so
ros_builtin_interfaces-2.3.0.data/data/include/builtin_interfaces/builtin_interfaces/msg/duration.h
ros_builtin_interfaces-2.3.0.data/data/include/builtin_interfaces/builtin_interfaces/msg/duration.hpp
ros_builtin_interfaces-2.3.0.data/data/include/builtin_interfaces/builtin_interfaces/msg/rosidl_generator_c__visibility_control.h
ros_builtin_interfaces-2.3.0.data/data/include/builtin_interfaces/builtin_interfaces/msg/rosidl_generator_cpp__visibility_control.hpp
ros_builtin_interfaces-2.3.0.data/data/include/builtin_interfaces/builtin_interfaces/msg/rosidl_typesupport_fastrtps_c__visibility_control.h
ros_builtin_interfaces-2.3.0.data/data/include/builtin_interfaces/builtin_interfaces/msg/rosidl_typesupport_fastrtps_cpp__visibility_control.h
ros_builtin_interfaces-2.3.0.data/data/include/builtin_interfaces/builtin_interfaces/msg/rosidl_typesupport_introspection_c__visibility_control.h
ros_builtin_interfaces-2.3.0.data/data/include/builtin_interfaces/builtin_interfaces/msg/time.h
ros_builtin_interfaces-2.3.0.data/data/include/builtin_interfaces/builtin_interfaces/msg/time.hpp
ros_builtin_interfaces-2.3.0.data/data/include/builtin_interfaces/builtin_interfaces/msg/detail/duration__builder.hpp
ros_builtin_interfaces-2.3.0.data/data/include/builtin_interfaces/builtin_interfaces/msg/detail/duration__description.c
ros_builtin_interfaces-2.3.0.data/data/include/builtin_interfaces/builtin_interfaces/msg/detail/duration__functions.c
ros_builtin_interfaces-2.3.0.data/data/include/builtin_interfaces/builtin_interfaces/msg/detail/duration__functions.h
ros_builtin_interfaces-2.3.0.data/data/include/builtin_interfaces/builtin_interfaces/msg/detail/duration__rosidl_typesupport_fastrtps_c.h
ros_builtin_interfaces-2.3.0.data/data/include/builtin_interfaces/builtin_interfaces/msg/detail/duration__rosidl_typesupport_fastrtps_cpp.hpp
ros_builtin_interfaces-2.3.0.data/data/lib/python3.13/site-packages/builtin_interfaces-2.3.0-py3.13.egg-info/PKG-INFO
ros_builtin_interfaces-2.3.0.data/data/lib/python3.13/site-packages/builtin_interfaces-2.3.0-py3.13.egg-info/SOURCES.txt
ros_builtin_interfaces-2.3.0.data/data/lib/python3.13/site-packages/builtin_interfaces-2.3.0-py3.13.egg-info/dependency_links.txt
ros_builtin_interfaces-2.3.0.data/data/lib/python3.13/site-packages/builtin_interfaces-2.3.0-py3.13.egg-info/top_level.txt
ros_builtin_interfaces-2.3.0.dist-info/METADATA
ros_builtin_interfaces-2.3.0.dist-info/WHEEL
ros_builtin_interfaces-2.3.0.dist-info/top_level.txt
ros_builtin_interfaces-2.3.0.dist-info/RECORD
