Metadata-Version: 2.4
Name: ros-builtin-interfaces
Version: 2.3.0
Summary: This ROS 2 package provides fundamental message definitions, including Duration and Time, based on the OMG IDL Platform Specific Model.
Requires-Dist: ros-rosidl-core-runtime~=0.3.1
Dynamic: description
Dynamic: description-content-type
Dynamic: requires-dist
Dynamic: summary
